priority_redis_queue/__init__.py
priority_redis_queue/conn.py
priority_redis_queue/py.typed
priority_redis_queue/queue.py
priority_redis_queue-0.0.4.dist-info/METADATA
priority_redis_queue-0.0.4.dist-info/WHEEL
priority_redis_queue-0.0.4.dist-info/entry_points.txt
priority_redis_queue-0.0.4.dist-info/RECORD
