Metadata-Version: 2.1
Name: priority_redis_queue
Version: 0.0.4
Summary: priority_redis_queue
Author: shubham-sentieo
Author-email: sentieodev@sentieo.com
Requires-Python: >=3.10,<4.0
Classifier: Programming Language :: Python :: 3
Classifier: Programming Language :: Python :: 3.10
Classifier: Programming Language :: Python :: 3.11
Classifier: Programming Language :: Python :: 3.12
Requires-Dist: redis (>=4.3.4,<5.0.0)
